starry/__init__.py
starry/_c_ops.cp37-win_amd64.pyd
starry/_config.py
starry/_constants.py
starry/_indices.py
starry/_plotting.py
starry/compat.py
starry/kepler.py
starry/legacy.py
starry/linalg.py
starry/maps.py
starry/starry_version.py
starry/_core/__init__.py
starry/_core/core.py
starry/_core/math.py
starry/_core/utils.py
starry/_core/ops/__init__.py
starry/_core/ops/exceptions.py
starry/_core/ops/filter.py
starry/_core/ops/integration.py
starry/_core/ops/minimize.py
starry/_core/ops/polybasis.py
starry/_core/ops/rotation.py
starry/_core/ops/spot.py
starry/_core/ops/lib/include/interface.cpp
starry/_core/ops/limbdark/__init__.py
starry/_core/ops/limbdark/base_op.py
starry/_core/ops/limbdark/get_cl.py
starry/_core/ops/limbdark/get_cl_rev.py
starry/_core/ops/limbdark/limbdark.py
starry/extensions/__init__.py
starry/extensions/nexsci/__init__.py
starry/extensions/nexsci/nexsci.py
starry/img/earth.png
starry/img/jupiter.png
starry/img/moon.png
starry/img/spot.png
starry-1.1.0.data/data/earth.png
starry-1.1.0.data/data/jupiter.png
starry-1.1.0.data/data/moon.png
starry-1.1.0.data/data/spot.png
starry-1.1.0.dist-info/LICENSE
starry-1.1.0.dist-info/METADATA
starry-1.1.0.dist-info/WHEEL
starry-1.1.0.dist-info/top_level.txt
starry-1.1.0.dist-info/RECORD
