Metadata-Version: 2.1
Name: starry
Version: 1.1.0
Summary: Analytic occultation light curves for astronomy.
Home-page: https://github.com/rodluger/starry
Author: Rodrigo Luger
Author-email: rodluger@gmail.com
License: MIT
Platform: UNKNOWN
Requires-Dist: setuptools-scm
Requires-Dist: numpy (>=1.19.2)
Requires-Dist: scipy (>=1.5.0)
Requires-Dist: astropy (>=3.1)
Requires-Dist: pymc3
Requires-Dist: pymc3-ext
Requires-Dist: matplotlib (>=3.2.2)
Requires-Dist: ipython
Requires-Dist: exoplanet (>=0.4.0)
Requires-Dist: packaging
Provides-Extra: docs
Requires-Dist: sphinx (>=1.7.5) ; extra == 'docs'
Requires-Dist: pandoc ; extra == 'docs'
Requires-Dist: jupyter ; extra == 'docs'
Requires-Dist: jupytext ; extra == 'docs'
Requires-Dist: ipywidgets ; extra == 'docs'
Requires-Dist: nbformat ; extra == 'docs'
Requires-Dist: nbconvert ; extra == 'docs'
Requires-Dist: rtds-action ; extra == 'docs'
Requires-Dist: nbsphinx ; extra == 'docs'
Requires-Dist: tqdm ; extra == 'docs'
Provides-Extra: tests
Requires-Dist: parameterized ; extra == 'tests'
Requires-Dist: nose ; extra == 'tests'
Requires-Dist: pytest ; extra == 'tests'
Requires-Dist: pytest-dependency ; extra == 'tests'
Requires-Dist: pytest-env ; extra == 'tests'
Requires-Dist: pytest-cov ; extra == 'tests'
Requires-Dist: scikit-image ; extra == 'tests'
Requires-Dist: pillow ; extra == 'tests'
Requires-Dist: tqdm ; extra == 'tests'
